tea/__init__.py
tea/api.py
tea/ast.py
tea/build.py
tea/global_vals.py
tea/helpers/__init__.py
tea/helpers/constants/__init__.py
tea/helpers/constants/default_values.py
tea/helpers/constants/test_names.py
tea/helpers/evaluateHelperMethods.py
tea/helpers/study_type_determiner.py
tea/logging/__init__.py
tea/logging/logging_target.py
tea/logging/tea_logger.py
tea/logging/tea_logger_configuration.py
tea/runtimeDataStructures/__init__.py
tea/runtimeDataStructures/bivariateData.py
tea/runtimeDataStructures/combinedData.py
tea/runtimeDataStructures/dataset.py
tea/runtimeDataStructures/multivariateData.py
tea/runtimeDataStructures/resultData.py
tea/runtimeDataStructures/testResult.py
tea/runtimeDataStructures/value.py
tea/runtimeDataStructures/varData.py
tea/tea_eval.py
tea/vardata_factory.py
tea/z3_solver/__init__.py
tea/z3_solver/solver.py
tealang-0.4.2.dist-info/LICENSE.md
tealang-0.4.2.dist-info/WHEEL
tealang-0.4.2.dist-info/METADATA
tealang-0.4.2.dist-info/RECORD
