Metadata-Version: 2.1
Name: tealang
Version: 0.4.2
Summary: Tea: A High-level Language and Runtime System to Automate Statistical Analysis
License: Apache 2.0
Author: Eunice Jun
Author-email: eunice.m.jun@gmail.com
Requires-Python: >=3.7.11,<3.11
Classifier: License :: Other/Proprietary License
Classifier: Programming Language :: Python :: 3
Classifier: Programming Language :: Python :: 3.8
Classifier: Programming Language :: Python :: 3.9
Requires-Dist: attrs (==21.4.0)
Requires-Dist: bootstrapped (==0.0.2)
Requires-Dist: pandas (==1.3.5)
Requires-Dist: parameterized (==0.8.1)
Requires-Dist: requests (==2.27.1)
Requires-Dist: scikit-learn (==1.0.2)
Requires-Dist: scipy (==1.7.3)
Requires-Dist: statsmodels (>=0.12.2,<0.13.0)
Requires-Dist: sympy (==1.9)
Requires-Dist: urllib3 (==1.26.8)
Requires-Dist: z3-solver (==4.8.14.0)
